FuClientForExam/AIclient.py
FuClientForExam/__init__.py
fuclientforexam-0.1.1.dist-info/METADATA
fuclientforexam-0.1.1.dist-info/WHEEL
fuclientforexam-0.1.1.dist-info/top_level.txt
fuclientforexam-0.1.1.dist-info/RECORD
