Metadata-Version: 2.4
Name: FuClientForExam
Version: 0.1.1
Summary: Python client for exam
Home-page: https://github.com/yourusername/aiclient
Author: VoNiRoNi
Author-email: alesha.vorobev2017@yandex.ru
Classifier: Programming Language :: Python :: 3
Classifier: License :: OSI Approved :: MIT License
Classifier: Operating System :: OS Independent
Requires-Python: >=3.6
Requires-Dist: requests>=2.25.1
Dynamic: author
Dynamic: author-email
Dynamic: classifier
Dynamic: description
Dynamic: description-content-type
Dynamic: home-page
Dynamic: requires-dist
Dynamic: requires-python
Dynamic: summary
